{
  "name": "modal",
  "type": "registry:ui",
  "title": "Modal",
  "description": "Base UI Dialog — real Motion-driven enter/exit, responsive bottom-sheet on mobile.",
  "registryDependencies": [
    "theme",
    "cn",
    "motion",
    "slot-class-names"
  ],
  "dependencies": [
    "@base-ui/react",
    "motion",
    "lucide-react"
  ],
  "files": [
    {
      "path": "packages/react/src/components/modal/modal.tsx",
      "type": "registry:ui",
      "content": "import * as React from \"react\";\nimport { Dialog } from \"@base-ui/react/dialog\";\nimport { motion } from \"motion/react\";\nimport { X } from \"lucide-react\";\nimport {\n  modalAnimations,\n  spring,\n  usePrefersReducedMotion,\n  type ModalAnimation,\n} from \"@/lib/avara-motion\";\nimport { modalBackdropVariants, modalViewportVariants, modalPopupVariants } from \"./modal.variants\";\n\nimport { cn } from \"@/lib/cn\";\nimport type { SlotClassNames } from \"@/lib/slot-class-names\";\n\nexport type ModalClassNames = SlotClassNames<\n  \"base\" | \"header\" | \"body\" | \"footer\" | \"backdrop\" | \"closeButton\"\n>;\ntype ModalSize = \"xs\" | \"sm\" | \"md\" | \"lg\" | \"xl\" | \"full\";\ntype ModalRadius = \"sm\" | \"md\" | \"lg\" | \"xl\";\ntype ModalBackdrop = \"transparent\" | \"opaque\" | \"blur\";\ntype ModalPlacement = \"auto\" | \"center\" | \"top\";\n\nexport interface ModalProps {\n  isOpen?: boolean;\n  defaultOpen?: boolean;\n  onOpenChange?: (isOpen: boolean) => void;\n  isDismissable?: boolean;\n  isKeyboardDismissDisabled?: boolean;\n  showCloseButton?: boolean;\n  size?: ModalSize;\n  radius?: ModalRadius;\n  backdrop?: ModalBackdrop;\n  placement?: ModalPlacement;\n  scrollBehavior?: \"inside\" | \"outside\";\n  animation?: ModalAnimation;\n  classNames?: ModalClassNames;\n  children: React.ReactNode;\n}\n\nconst backdropFade = {\n  initial: { opacity: 0 },\n  animate: { opacity: 1 },\n  exit: { opacity: 0 },\n};\n\nconst ModalRoot = ({\n  isOpen,\n  defaultOpen,\n  onOpenChange,\n  isDismissable = true,\n  isKeyboardDismissDisabled = false,\n  showCloseButton = true,\n  size,\n  radius,\n  backdrop,\n  placement,\n  scrollBehavior = \"outside\",\n  animation = \"scale\",\n  classNames,\n  children,\n}: ModalProps) => {\n  const actionsRef = React.useRef<{ unmount: () => void; close: () => void } | null>(null);\n  const prefersReducedMotion = usePrefersReducedMotion();\n  const variants = modalAnimations[prefersReducedMotion ? \"none\" : animation];\n\n  return (\n    <Dialog.Root\n      open={isOpen}\n      defaultOpen={defaultOpen}\n      modal\n      actionsRef={actionsRef}\n      disablePointerDismissal={!isDismissable}\n      onOpenChange={(open, eventDetails) => {\n        if (!open && isKeyboardDismissDisabled && eventDetails.reason === \"escape-key\") {\n          eventDetails.cancel();\n          return;\n        }\n        if (!open) {\n          // Keep Popup/Backdrop mounted so Motion can play the exit animation;\n          // we manually unmount once it finishes (see onAnimationComplete below).\n          eventDetails.preventUnmountOnClose();\n        }\n        onOpenChange?.(open);\n      }}\n    >\n      <Dialog.Portal>\n        <Dialog.Backdrop\n          render={(props, state) => {\n            /* eslint-disable @typescript-eslint/no-unused-vars -- destructured only to exclude from the spread below (React/Motion event type conflict) */\n            const {\n              onDrag,\n              onDragStart,\n              onDragEnd,\n              onAnimationStart,\n              onAnimationEnd,\n              ...restProps\n            } = props;\n            /* eslint-enable @typescript-eslint/no-unused-vars */\n            return (\n              <motion.div\n                {...restProps}\n                initial=\"initial\"\n                animate={state.open ? \"animate\" : \"exit\"}\n                variants={backdropFade}\n                transition={prefersReducedMotion ? { duration: 0 } : { duration: 0.2 }}\n                className={cn(modalBackdropVariants({ backdrop }), classNames?.backdrop)}\n              />\n            );\n          }}\n        />\n        <div className={cn(modalViewportVariants({ placement }))}>\n          <Dialog.Popup\n            render={(props, state) => {\n              /* eslint-disable @typescript-eslint/no-unused-vars -- destructured only to exclude from the spread below (React/Motion event type conflict) */\n              const {\n                onDrag,\n                onDragStart,\n                onDragEnd,\n                onAnimationStart,\n                onAnimationEnd,\n                ...restProps\n              } = props;\n              /* eslint-enable @typescript-eslint/no-unused-vars */\n              return (\n                <motion.div\n                  {...restProps}\n                  initial=\"initial\"\n                  animate={state.open ? \"animate\" : \"exit\"}\n                  variants={variants}\n                  transition={spring.snappy}\n                  onAnimationComplete={(definition) => {\n                    if (definition === \"exit\") {\n                      actionsRef.current?.unmount();\n                    }\n                  }}\n                  className={cn(\n                    modalPopupVariants({ size, radius, placement }),\n                    scrollBehavior === \"inside\" && \"max-h-[85vh]\",\n                    classNames?.base,\n                  )}\n                >\n                  {showCloseButton && (\n                    <Dialog.Close\n                      className={cn(\n                        \"absolute right-4 top-4 rounded-md text-muted transition-colors hover:text-foreground\",\n                        classNames?.closeButton,\n                      )}\n                      aria-label=\"Close\"\n                    >\n                      <X className=\"size-4\" />\n                    </Dialog.Close>\n                  )}\n                  {restProps.children}\n                </motion.div>\n              );\n            }}\n          >\n            {children}\n          </Dialog.Popup>\n        </div>\n      </Dialog.Portal>\n    </Dialog.Root>\n  );\n};\nModalRoot.displayName = \"Modal\";\n\nconst ModalHeader = ({ className, ...props }: React.ComponentPropsWithoutRef<\"div\">) => (\n  <div\n    className={cn(\"flex flex-col gap-1 border-b border-border px-6 py-4\", className)}\n    {...props}\n  />\n);\nModalHeader.displayName = \"Modal.Header\";\n\nconst ModalTitle = ({\n  className,\n  ...props\n}: React.ComponentPropsWithoutRef<typeof Dialog.Title>) => (\n  <Dialog.Title className={cn(\"text-lg font-extrabold\", className)} {...props} />\n);\nModalTitle.displayName = \"Modal.Title\";\n\nconst ModalDescription = ({\n  className,\n  ...props\n}: React.ComponentPropsWithoutRef<typeof Dialog.Description>) => (\n  <Dialog.Description className={cn(\"text-sm text-muted\", className)} {...props} />\n);\nModalDescription.displayName = \"Modal.Description\";\n\nconst ModalBody = ({ className, ...props }: React.ComponentPropsWithoutRef<\"div\">) => (\n  <div className={cn(\"flex-1 overflow-y-auto px-6 py-4\", className)} {...props} />\n);\nModalBody.displayName = \"Modal.Body\";\n\nconst ModalFooter = ({ className, ...props }: React.ComponentPropsWithoutRef<\"div\">) => (\n  <div\n    className={cn(\n      \"flex items-center justify-end gap-2 border-t border-border px-6 py-4\",\n      className,\n    )}\n    {...props}\n  />\n);\nModalFooter.displayName = \"Modal.Footer\";\n\nexport const Modal = Object.assign(ModalRoot, {\n  Header: ModalHeader,\n  Title: ModalTitle,\n  Description: ModalDescription,\n  Body: ModalBody,\n  Footer: ModalFooter,\n});\n"
    },
    {
      "path": "packages/react/src/components/modal/modal.variants.ts",
      "type": "registry:ui",
      "content": "import { cva } from \"class-variance-authority\";\n\nexport const modalBackdropVariants = cva(\"fixed inset-0\", {\n  variants: {\n    backdrop: {\n      transparent: \"bg-transparent\",\n      opaque: \"bg-black/50 dark:bg-black/70\",\n      blur: \"bg-black/30 dark:bg-black/50 backdrop-blur-md\",\n    },\n  },\n  defaultVariants: {\n    backdrop: \"opaque\",\n  },\n});\n\nexport const modalViewportVariants = cva(\"fixed inset-0 flex justify-center overflow-y-auto\", {\n  variants: {\n    placement: {\n      auto: \"items-end p-0 sm:items-center sm:p-4\",\n      center: \"items-center p-4\",\n      top: \"items-start pt-16 p-4\",\n    },\n  },\n  defaultVariants: {\n    placement: \"auto\",\n  },\n});\n\nexport const modalPopupVariants = cva(\n  \"relative w-full flex flex-col bg-surface text-foreground border border-border shadow-lg outline-none relative w-full flex flex-col bg-surface border border-border shadow-lg outline-none backdrop-blur-(--glass-blur) backdrop-saturate-(--glass-saturate)\",\n  {\n    variants: {\n      size: {\n        xs: \"max-w-xs\",\n        sm: \"max-w-sm\",\n        md: \"max-w-md\",\n        lg: \"max-w-lg\",\n        xl: \"max-w-xl\",\n        full: \"max-w-none h-full\",\n      },\n      radius: {\n        sm: \"rounded-sm\",\n        md: \"rounded-md\",\n        lg: \"rounded-lg\",\n        xl: \"rounded-xl\",\n      },\n      placement: {\n        auto: \"max-sm:w-full max-sm:rounded-t-xl max-sm:rounded-b-none max-sm:border-x-0 max-sm:border-b-0\",\n        center: \"\",\n        top: \"\",\n      },\n    },\n    compoundVariants: [\n      // Full-screen never has rounded corners, regardless of the radius prop\n      { size: \"full\", radius: \"sm\", class: \"rounded-none\" },\n      { size: \"full\", radius: \"md\", class: \"rounded-none\" },\n      { size: \"full\", radius: \"lg\", class: \"rounded-none\" },\n      { size: \"full\", radius: \"xl\", class: \"rounded-none\" },\n    ],\n    defaultVariants: {\n      size: \"md\",\n      radius: \"lg\",\n      placement: \"auto\",\n    },\n  },\n);\n"
    }
  ]
}